{
    "swagger": "2.0",
    "info": {
        "description": "Response containing user's group information",
        "title": "NounHub Authentication API",
        "contact": {
            "name": "NounHub API Support",
            "url": "https://www.nounhub.org"
        },
        "version": "1.0"
    },
    "basePath": "/{stage}",
    "paths": {
        "/auth/confirm": {
            "post": {
                "description": "Confirms a user's account using the verification code",
                "consumes": [
                    "application/json"
                ],
                "produces": [
                    "application/json"
                ],
                "tags": [
                    "Authentication"
                ],
                "summary": "Confirm user account",
                "parameters": [
                    {
                        "description": "Confirmation details",
                        "name": "request",
                        "in": "body",
                        "required": true,
                        "schema": {
                            "type": "object"
                        }
                    }
                ],
                "responses": {
                    "200": {
                        "description": "Account confirmed successfully",
                        "schema": {
                            "$ref": "#/definitions/main.APIResponse"
                        }
                    },
                    "400": {
                        "description": "Bad request",
                        "schema": {
                            "$ref": "#/definitions/main.APIResponse"
                        }
                    },
                    "404": {
                        "description": "Account not found",
                        "schema": {
                            "$ref": "#/definitions/main.APIResponse"
                        }
                    },
                    "500": {
                        "description": "Internal server error",
                        "schema": {
                            "$ref": "#/definitions/main.APIResponse"
                        }
                    }
                }
            }
        },
        "/auth/confirm-forgot-password": {
            "post": {
                "description": "Resets the user's password using the verification code",
                "consumes": [
                    "application/json"
                ],
                "produces": [
                    "application/json"
                ],
                "tags": [
                    "Authentication"
                ],
                "summary": "Reset password",
                "parameters": [
                    {
                        "description": "Password reset confirmation",
                        "name": "request",
                        "in": "body",
                        "required": true,
                        "schema": {
                            "$ref": "#/definitions/main.ConfirmForgotPasswordRequest"
                        }
                    }
                ],
                "responses": {
                    "200": {
                        "description": "Password reset successful",
                        "schema": {
                            "$ref": "#/definitions/main.APIResponse"
                        }
                    },
                    "400": {
                        "description": "Bad request",
                        "schema": {
                            "$ref": "#/definitions/main.APIResponse"
                        }
                    },
                    "404": {
                        "description": "Account not found",
                        "schema": {
                            "$ref": "#/definitions/main.APIResponse"
                        }
                    },
                    "500": {
                        "description": "Internal server error",
                        "schema": {
                            "$ref": "#/definitions/main.APIResponse"
                        }
                    }
                }
            }
        },
        "/auth/forgot-password": {
            "post": {
                "description": "Sends a password reset code to the user's email",
                "consumes": [
                    "application/json"
                ],
                "produces": [
                    "application/json"
                ],
                "tags": [
                    "Authentication"
                ],
                "summary": "Request password reset",
                "parameters": [
                    {
                        "description": "Password reset request",
                        "name": "request",
                        "in": "body",
                        "required": true,
                        "schema": {
                            "$ref": "#/definitions/main.ForgotPasswordRequest"
                        }
                    }
                ],
                "responses": {
                    "200": {
                        "description": "Password reset code sent",
                        "schema": {
                            "$ref": "#/definitions/main.APIResponse"
                        }
                    },
                    "400": {
                        "description": "Bad request",
                        "schema": {
                            "$ref": "#/definitions/main.APIResponse"
                        }
                    },
                    "404": {
                        "description": "Account not found",
                        "schema": {
                            "$ref": "#/definitions/main.APIResponse"
                        }
                    },
                    "500": {
                        "description": "Internal server error",
                        "schema": {
                            "$ref": "#/definitions/main.APIResponse"
                        }
                    }
                }
            }
        },
        "/auth/google": {
            "post": {
                "description": "Authenticates a user with a Google OAuth token",
                "consumes": [
                    "application/json"
                ],
                "produces": [
                    "application/json"
                ],
                "tags": [
                    "Authentication"
                ],
                "summary": "Sign in with Google",
                "parameters": [
                    {
                        "description": "Google OAuth token",
                        "name": "request",
                        "in": "body",
                        "required": true,
                        "schema": {
                            "type": "object"
                        }
                    }
                ],
                "responses": {
                    "200": {
                        "description": "Successfully authenticated with Google",
                        "schema": {
                            "$ref": "#/definitions/main.APIResponse"
                        }
                    },
                    "400": {
                        "description": "Bad request",
                        "schema": {
                            "$ref": "#/definitions/main.APIResponse"
                        }
                    },
                    "500": {
                        "description": "Internal server error",
                        "schema": {
                            "$ref": "#/definitions/main.APIResponse"
                        }
                    }
                }
            }
        },
        "/auth/groups": {
            "get": {
                "security": [
                    {
                        "BearerAuth": []
                    }
                ],
                "description": "Lists all available user groups",
                "consumes": [
                    "application/json"
                ],
                "produces": [
                    "application/json"
                ],
                "tags": [
                    "Groups"
                ],
                "summary": "List groups",
                "responses": {
                    "200": {
                        "description": "Groups retrieved successfully",
                        "schema": {
                            "allOf": [
                                {
                                    "$ref": "#/definitions/main.APIResponse"
                                },
                                {
                                    "type": "object",
                                    "properties": {
                                        "data": {
                                            "type": "array",
                                            "items": {
                                                "$ref": "#/definitions/main.GroupResponse"
                                            }
                                        }
                                    }
                                }
                            ]
                        }
                    },
                    "401": {
                        "description": "Unauthorized",
                        "schema": {
                            "$ref": "#/definitions/main.APIResponse"
                        }
                    },
                    "500": {
                        "description": "Internal server error",
                        "schema": {
                            "$ref": "#/definitions/main.APIResponse"
                        }
                    }
                }
            }
        },
        "/auth/groups/{group_name}/users": {
            "get": {
                "security": [
                    {
                        "BearerAuth": []
                    }
                ],
                "description": "Lists all users in a specific group",
                "consumes": [
                    "application/json"
                ],
                "produces": [
                    "application/json"
                ],
                "tags": [
                    "Groups"
                ],
                "summary": "List users in group",
                "parameters": [
                    {
                        "type": "string",
                        "description": "Group name",
                        "name": "group_name",
                        "in": "path",
                        "required": true
                    }
                ],
                "responses": {
                    "200": {
                        "description": "Users in group retrieved successfully",
                        "schema": {
                            "allOf": [
                                {
                                    "$ref": "#/definitions/main.APIResponse"
                                },
                                {
                                    "type": "object",
                                    "properties": {
                                        "data": {
                                            "type": "array",
                                            "items": {
                                                "type": "string"
                                            }
                                        }
                                    }
                                }
                            ]
                        }
                    },
                    "400": {
                        "description": "Bad request",
                        "schema": {
                            "$ref": "#/definitions/main.APIResponse"
                        }
                    },
                    "401": {
                        "description": "Unauthorized",
                        "schema": {
                            "$ref": "#/definitions/main.APIResponse"
                        }
                    },
                    "403": {
                        "description": "Forbidden",
                        "schema": {
                            "$ref": "#/definitions/main.APIResponse"
                        }
                    },
                    "500": {
                        "description": "Internal server error",
                        "schema": {
                            "$ref": "#/definitions/main.APIResponse"
                        }
                    }
                }
            },
            "post": {
                "security": [
                    {
                        "BearerAuth": []
                    }
                ],
                "description": "Adds a user to a specific group",
                "consumes": [
                    "application/json"
                ],
                "produces": [
                    "application/json"
                ],
                "tags": [
                    "Groups"
                ],
                "summary": "Add user to group",
                "parameters": [
                    {
                        "type": "string",
                        "description": "Group name",
                        "name": "group_name",
                        "in": "path",
                        "required": true
                    },
                    {
                        "description": "User details",
                        "name": "request",
                        "in": "body",
                        "required": true,
                        "schema": {
                            "type": "object"
                        }
                    }
                ],
                "responses": {
                    "200": {
                        "description": "User added to group successfully",
                        "schema": {
                            "$ref": "#/definitions/main.APIResponse"
                        }
                    },
                    "400": {
                        "description": "Bad request",
                        "schema": {
                            "$ref": "#/definitions/main.APIResponse"
                        }
                    },
                    "401": {
                        "description": "Unauthorized",
                        "schema": {
                            "$ref": "#/definitions/main.APIResponse"
                        }
                    },
                    "403": {
                        "description": "Forbidden",
                        "schema": {
                            "$ref": "#/definitions/main.APIResponse"
                        }
                    },
                    "404": {
                        "description": "User not found",
                        "schema": {
                            "$ref": "#/definitions/main.APIResponse"
                        }
                    },
                    "500": {
                        "description": "Internal server error",
                        "schema": {
                            "$ref": "#/definitions/main.APIResponse"
                        }
                    }
                }
            }
        },
        "/auth/groups/{group_name}/users/{username}": {
            "delete": {
                "security": [
                    {
                        "BearerAuth": []
                    }
                ],
                "description": "Removes a user from a specific group",
                "consumes": [
                    "application/json"
                ],
                "produces": [
                    "application/json"
                ],
                "tags": [
                    "Groups"
                ],
                "summary": "Remove user from group",
                "parameters": [
                    {
                        "type": "string",
                        "description": "Group name",
                        "name": "group_name",
                        "in": "path",
                        "required": true
                    },
                    {
                        "type": "string",
                        "description": "Username",
                        "name": "username",
                        "in": "path",
                        "required": true
                    }
                ],
                "responses": {
                    "200": {
                        "description": "User removed from group successfully",
                        "schema": {
                            "$ref": "#/definitions/main.APIResponse"
                        }
                    },
                    "400": {
                        "description": "Bad request",
                        "schema": {
                            "$ref": "#/definitions/main.APIResponse"
                        }
                    },
                    "401": {
                        "description": "Unauthorized",
                        "schema": {
                            "$ref": "#/definitions/main.APIResponse"
                        }
                    },
                    "403": {
                        "description": "Forbidden",
                        "schema": {
                            "$ref": "#/definitions/main.APIResponse"
                        }
                    },
                    "404": {
                        "description": "User not found",
                        "schema": {
                            "$ref": "#/definitions/main.APIResponse"
                        }
                    },
                    "500": {
                        "description": "Internal server error",
                        "schema": {
                            "$ref": "#/definitions/main.APIResponse"
                        }
                    }
                }
            }
        },
        "/auth/profile": {
            "get": {
                "security": [
                    {
                        "BearerAuth": []
                    }
                ],
                "description": "Retrieves the profile information for the authenticated user",
                "consumes": [
                    "application/json"
                ],
                "produces": [
                    "application/json"
                ],
                "tags": [
                    "Profile"
                ],
                "summary": "Get user profile",
                "responses": {
                    "200": {
                        "description": "Profile retrieved successfully",
                        "schema": {
                            "allOf": [
                                {
                                    "$ref": "#/definitions/main.APIResponse"
                                },
                                {
                                    "type": "object",
                                    "properties": {
                                        "data": {
                                            "$ref": "#/definitions/main.UserProfileResponse"
                                        }
                                    }
                                }
                            ]
                        }
                    },
                    "401": {
                        "description": "Unauthorized",
                        "schema": {
                            "$ref": "#/definitions/main.APIResponse"
                        }
                    },
                    "500": {
                        "description": "Internal server error",
                        "schema": {
                            "$ref": "#/definitions/main.APIResponse"
                        }
                    }
                }
            }
        },
        "/auth/refresh": {
            "post": {
                "description": "Refreshes the access token using a valid refresh token",
                "consumes": [
                    "application/json"
                ],
                "produces": [
                    "application/json"
                ],
                "tags": [
                    "Authentication"
                ],
                "summary": "Refresh access token",
                "parameters": [
                    {
                        "description": "Refresh token request",
                        "name": "request",
                        "in": "body",
                        "required": true,
                        "schema": {
                            "$ref": "#/definitions/main.RefreshTokenRequest"
                        }
                    }
                ],
                "responses": {
                    "200": {
                        "description": "Tokens refreshed successfully",
                        "schema": {
                            "allOf": [
                                {
                                    "$ref": "#/definitions/main.APIResponse"
                                },
                                {
                                    "type": "object",
                                    "properties": {
                                        "data": {
                                            "type": "object",
                                            "additionalProperties": true
                                        }
                                    }
                                }
                            ]
                        }
                    },
                    "400": {
                        "description": "Bad request",
                        "schema": {
                            "$ref": "#/definitions/main.APIResponse"
                        }
                    },
                    "401": {
                        "description": "Invalid token",
                        "schema": {
                            "$ref": "#/definitions/main.APIResponse"
                        }
                    },
                    "500": {
                        "description": "Internal server error",
                        "schema": {
                            "$ref": "#/definitions/main.APIResponse"
                        }
                    }
                }
            }
        },
        "/auth/resend-confirmation": {
            "post": {
                "description": "Resends the account confirmation code to the user's email",
                "consumes": [
                    "application/json"
                ],
                "produces": [
                    "application/json"
                ],
                "tags": [
                    "Authentication"
                ],
                "summary": "Resend confirmation code",
                "parameters": [
                    {
                        "description": "Email details",
                        "name": "request",
                        "in": "body",
                        "required": true,
                        "schema": {
                            "type": "object"
                        }
                    }
                ],
                "responses": {
                    "200": {
                        "description": "Confirmation code sent",
                        "schema": {
                            "$ref": "#/definitions/main.APIResponse"
                        }
                    },
                    "400": {
                        "description": "Bad request",
                        "schema": {
                            "$ref": "#/definitions/main.APIResponse"
                        }
                    },
                    "404": {
                        "description": "Account not found",
                        "schema": {
                            "$ref": "#/definitions/main.APIResponse"
                        }
                    },
                    "500": {
                        "description": "Internal server error",
                        "schema": {
                            "$ref": "#/definitions/main.APIResponse"
                        }
                    }
                }
            }
        },
        "/auth/signin": {
            "post": {
                "description": "Authenticates a user with email and password",
                "consumes": [
                    "application/json"
                ],
                "produces": [
                    "application/json"
                ],
                "tags": [
                    "Authentication"
                ],
                "summary": "Sign in to an existing account",
                "parameters": [
                    {
                        "description": "Sign in request",
                        "name": "request",
                        "in": "body",
                        "required": true,
                        "schema": {
                            "$ref": "#/definitions/main.SignInRequest"
                        }
                    }
                ],
                "responses": {
                    "200": {
                        "description": "Successfully authenticated",
                        "schema": {
                            "$ref": "#/definitions/main.APIResponse"
                        }
                    },
                    "400": {
                        "description": "Bad request",
                        "schema": {
                            "$ref": "#/definitions/main.APIResponse"
                        }
                    },
                    "401": {
                        "description": "Invalid credentials",
                        "schema": {
                            "$ref": "#/definitions/main.APIResponse"
                        }
                    },
                    "500": {
                        "description": "Internal server error",
                        "schema": {
                            "$ref": "#/definitions/main.APIResponse"
                        }
                    }
                }
            }
        },
        "/auth/signout": {
            "post": {
                "security": [
                    {
                        "BearerAuth": []
                    }
                ],
                "description": "Signs out the user from the current session or all sessions",
                "consumes": [
                    "application/json"
                ],
                "produces": [
                    "application/json"
                ],
                "tags": [
                    "Authentication"
                ],
                "summary": "Sign out",
                "parameters": [
                    {
                        "description": "Sign out request",
                        "name": "request",
                        "in": "body",
                        "required": true,
                        "schema": {
                            "$ref": "#/definitions/main.SignOutRequest"
                        }
                    }
                ],
                "responses": {
                    "200": {
                        "description": "Signed out successfully",
                        "schema": {
                            "$ref": "#/definitions/main.APIResponse"
                        }
                    },
                    "400": {
                        "description": "Bad request",
                        "schema": {
                            "$ref": "#/definitions/main.APIResponse"
                        }
                    },
                    "401": {
                        "description": "Unauthorized",
                        "schema": {
                            "$ref": "#/definitions/main.APIResponse"
                        }
                    },
                    "500": {
                        "description": "Internal server error",
                        "schema": {
                            "$ref": "#/definitions/main.APIResponse"
                        }
                    }
                }
            }
        },
        "/auth/signup": {
            "post": {
                "description": "Creates a new user account with the provided email and password",
                "consumes": [
                    "application/json"
                ],
                "produces": [
                    "application/json"
                ],
                "tags": [
                    "Authentication"
                ],
                "summary": "Create a new user account",
                "parameters": [
                    {
                        "description": "Sign up request",
                        "name": "request",
                        "in": "body",
                        "required": true,
                        "schema": {
                            "$ref": "#/definitions/main.SignUpRequest"
                        }
                    }
                ],
                "responses": {
                    "200": {
                        "description": "Account created successfully",
                        "schema": {
                            "$ref": "#/definitions/main.APIResponse"
                        }
                    },
                    "400": {
                        "description": "Bad request",
                        "schema": {
                            "$ref": "#/definitions/main.APIResponse"
                        }
                    },
                    "500": {
                        "description": "Internal server error",
                        "schema": {
                            "$ref": "#/definitions/main.APIResponse"
                        }
                    }
                }
            }
        },
        "/auth/users/{username}/groups": {
            "get": {
                "security": [
                    {
                        "BearerAuth": []
                    }
                ],
                "description": "Lists all groups a user belongs to",
                "consumes": [
                    "application/json"
                ],
                "produces": [
                    "application/json"
                ],
                "tags": [
                    "Groups"
                ],
                "summary": "List user groups",
                "parameters": [
                    {
                        "type": "string",
                        "description": "Username",
                        "name": "username",
                        "in": "path",
                        "required": true
                    }
                ],
                "responses": {
                    "200": {
                        "description": "User groups retrieved successfully",
                        "schema": {
                            "allOf": [
                                {
                                    "$ref": "#/definitions/main.APIResponse"
                                },
                                {
                                    "type": "object",
                                    "properties": {
                                        "data": {
                                            "type": "array",
                                            "items": {
                                                "type": "string"
                                            }
                                        }
                                    }
                                }
                            ]
                        }
                    },
                    "400": {
                        "description": "Bad request",
                        "schema": {
                            "$ref": "#/definitions/main.APIResponse"
                        }
                    },
                    "401": {
                        "description": "Unauthorized",
                        "schema": {
                            "$ref": "#/definitions/main.APIResponse"
                        }
                    },
                    "403": {
                        "description": "Forbidden",
                        "schema": {
                            "$ref": "#/definitions/main.APIResponse"
                        }
                    },
                    "500": {
                        "description": "Internal server error",
                        "schema": {
                            "$ref": "#/definitions/main.APIResponse"
                        }
                    }
                }
            }
        }
    },
    "definitions": {
        "main.APIResponse": {
            "description": "Standard response format for all API endpoints",
            "type": "object",
            "properties": {
                "data": {
                    "description": "Response data (if any)"
                },
                "error": {
                    "description": "Error message (if any)",
                    "type": "string",
                    "example": "Invalid input provided"
                },
                "message": {
                    "description": "Human-readable message about the result",
                    "type": "string",
                    "example": "Operation completed successfully"
                },
                "success": {
                    "description": "Indicates if the operation was successful",
                    "type": "boolean",
                    "example": true
                }
            }
        },
        "main.ConfirmForgotPasswordRequest": {
            "type": "object",
            "properties": {
                "code": {
                    "description": "Verification code sent to the user's email",
                    "type": "string",
                    "example": "123456"
                },
                "email": {
                    "description": "User's email address",
                    "type": "string",
                    "example": "offorsomto50@gmail.com"
                },
                "new_password": {
                    "description": "New password to set",
                    "type": "string",
                    "example": "NewPassword123!"
                }
            }
        },
        "main.ForgotPasswordRequest": {
            "type": "object",
            "properties": {
                "email": {
                    "description": "User's email address",
                    "type": "string",
                    "example": "offorsomto50@gmail.com"
                }
            }
        },
        "main.GroupResponse": {
            "description": "Response containing group information",
            "type": "object",
            "properties": {
                "description": {
                    "description": "Description of the group",
                    "type": "string",
                    "example": "System administrators group"
                },
                "name": {
                    "description": "Name of the group",
                    "type": "string",
                    "example": "admin"
                }
            }
        },
        "main.RefreshTokenRequest": {
            "type": "object",
            "properties": {
                "refresh_token": {
                    "description": "Refresh token received during sign in",
                    "type": "string",
                    "example": "eyJhbGciOiJIUzI1NiIsInR5cCI6IkpXVCJ9..."
                }
            }
        },
        "main.SignInRequest": {
            "type": "object",
            "properties": {
                "email": {
                    "description": "User's email address",
                    "type": "string",
                    "example": "offorsomto50@gmail.com"
                },
                "password": {
                    "description": "User's password",
                    "type": "string",
                    "example": "Password123!"
                }
            }
        },
        "main.SignOutRequest": {
            "type": "object",
            "properties": {
                "global": {
                    "description": "Whether to invalidate tokens on all devices",
                    "type": "boolean",
                    "example": true
                }
            }
        },
        "main.SignUpRequest": {
            "type": "object",
            "properties": {
                "email": {
                    "description": "User's email address",
                    "type": "string",
                    "example": "offorsomto50@gmail.com"
                },
                "password": {
                    "description": "User's password (must be at least 6 characters)",
                    "type": "string",
                    "example": "Password123!"
                }
            }
        },
        "main.UserProfileResponse": {
            "type": "object",
            "properties": {
                "email": {
                    "description": "User's email address",
                    "type": "string",
                    "example": "offorsomto50@gmail.com"
                },
                "linked_providers": {
                    "description": "List of authentication providers linked to this account",
                    "type": "array",
                    "items": {
                        "type": "string"
                    },
                    "example": [
                        "[\"google\"]"
                    ]
                },
                "username": {
                    "description": "User's unique username (UUID)",
                    "type": "string",
                    "example": "123e4567-e89b-12d3-a456-426614174000"
                }
            }
        }
    },
    "securityDefinitions": {
        "BearerAuth": {
            "description": "Enter the token with the `Bearer: ` prefix, e.g. \"Bearer abcde12345\".",
            "type": "apiKey",
            "name": "Authorization",
            "in": "header"
        }
    }
}